{"lightbulb": "lightbulb", "shoes": "shoes", "deck": "deck", "laptop": "laptop", "ceramic": "ceramic", "paper": "paper", "vacuum": "vacuum", "keyboard": "keyboard", "chair": "chair", "milk": "milk", "roots": "roots", "carpet": "carpet", "sauce": "sauce", "tire": "tire", "mud": "mud", "sky": "sky", "lake": "lake", "sugar": "sugar", "bush": "bush", "bike": "bike", "fig": "fig", "garage": "garage", "orange": "orange", "furniture": "furniture", "hat": "hat", "persimmon": "persimmon", "boulder": "boulder", "plate": "plate", "coffee": "coffee", "handle": "handle", "branch": "branch", "wire": "wire", "bear": "bear", "coast": "coast", "vegetable": "vegetable", "bean": "bean", "tulip": "tulip", "fan": "fan", "snake": "snake", "desk": "desk", "silk": "silk", "bread": "bread", "aluminum": "aluminum", "cable": "cable", "gemstone": "gemstone", "bracelet": "bracelet", "candy": "candy", "bay": "bay", "bag": "bag", "sand": "sand", "steps": "steps", "knife": "knife", "clay": "clay", "iguana": "iguana", "tower": "tower", "river": "river", "garden": "garden", "clothes": "clothes", "copper": "copper", "creek": "creek", "fence": "fence", "house": "house", "fish": "fish", "library": "library", "chocolate": "chocolate", "computer": "computer", "palm": "palm", "roof": "roof", "sea": "sea", "mirror": "mirror", "candle": "candle", "lightning": "lightning", "chicken": "chicken", "ribbon": "ribbon", "redwood": "redwood", "shower": "shower", "flower": "flower", "leaf": "leaf", "jewelry": "jewelry", "lead": "lead", "clock": "clock", "armor": "armor", "tube": "tube", "ice": "ice", "granite": "granite", "sword": "sword", "cloud": "cloud", "ground": "ground", "chains": "chains", "nest": "nest", "highway": "highway", "pants": "pants", "cord": "cord", "hose": "hose", "dirt": "dirt", "salmon": "salmon", "rock": "rock", "horse": "horse", "water": "water", "newspaper": "newspaper", "cookie": "cookie", "key": "key", "pasta": "pasta", "paste": "paste", "trail": "trail", "card": "card", "kitchen": "kitchen", "box": "box", "stone": "stone", "drum": "drum", "thread": "thread", "column": "column", "island": "island", "tie": "tie", "berry": "berry", "smoke": "smoke", "castle": "castle", "glasses": "glasses", "road": "road", "cheese": "cheese", "apple": "apple", "wall": "wall", "pot": "pot", "canyon": "canyon", "tomato": "tomato", "frame": "frame", "church": "church", "table": "table", "ring": "ring", "brass": "brass", "boat": "boat", "belt": "belt", "city": "city", "bathroom": "bathroom", "toy": "toy", "fabric": "fabric", "beef": "beef", "window": "window", "tree": "tree", "plastic": "plastic", "paint": "paint", "camera": "camera", "bronze": "bronze", "tea": "tea", "valley": "valley", "bubble": "bubble", "banana": "banana", "building": "building", "ceiling": "ceiling", "diamond": "diamond", "door": "door", "gear": "gear", "shorts": "shorts", "fire": "fire", "bus": "bus", "wax": "wax", "envelope": "envelope", "oil": "oil", "cabinet": "cabinet", "tiger": "tiger", "glass": "glass", "nut": "nut", "potato": "potato", "steel": "steel", "wood": "wood", "wool": "wool", "room": "room", "salad": "salad", "car": "car", "blade": "blade", "bucket": "bucket", "bed": "bed", "cat": "cat", "rope": "rope", "soup": "soup", "street": "street", "flame": "flame", "cake": "cake", "bridge": "bridge", "stream": "stream", "well": "well", "penny": "penny", "pie": "pie", "shell": "shell", "pond": "pond", "ocean": "ocean", "dress": "dress", "cotton": "cotton", "mountain": "mountain", "sandwich": "sandwich", "lemon": "lemon", "shirt": "shirt", "concrete": "concrete", "town": "town", "balloon": "balloon", "cave": "cave", "bowl": "bowl", "snow": "snow", "rubber": "rubber", "field": "field", "book": "book", "forest": "forest", "animal": "animal", "elephant": "elephant", "tile": "tile", "gate": "gate", "beach": "beach", "pizza": "pizza", "wheel": "wheel", "wave": "wave", "plant": "plant", "ball": "ball", "mat": "mat", "screw": "screw", "farm": "farm", "eggs": "eggs", "foam": "foam", "pear": "pear", "necklace": "necklace", "fruit": "fruit", "garlic": "garlic", "log": "log", "moss": "moss", "dust": "dust", "velvet": "velvet", "basement": "basement", "coin": "coin", "desert": "desert", "pool": "pool", "cliff": "cliff", "butter": "butter", "phone": "phone", "coat": "coat", "seafood": "seafood", "floor": "floor", "metal": "metal", "dog": "dog", "meat": "meat", "jacket": "jacket", "coal": "coal", "shore": "shore", "truck": "truck", "jungle": "jungle", "bottle": "bottle", "basket": "basket"}