{"crumpled": "crumpled", "upright": "upright", "bright": "bright", "rough": "rough", "shattered": "shattered", "cut": "cut", "torn": "torn", "folded": "folded", "young": "young", "wet": "wet", "cluttered": "cluttered", "verdant": "verdant", "sunny": "sunny", "runny": "runny", "thawed": "thawed", "dark": "dark", "windblown": "windblown", "burnt": "burnt", "molten": "molten", "eroded": "eroded", "frayed": "frayed", "blunt": "blunt", "cloudy": "cloudy", "large": "large", "whipped": "whipped", "small": "small", "engraved": "engraved", "heavy": "heavy", "old": "old", "thin": "thin", "diced": "diced", "rusty": "rusty", "inflated": "inflated", "ruffled": "ruffled", "steaming": "steaming", "unpainted": "unpainted", "moldy": "moldy", "closed": "closed", "new": "new", "filled": "filled", "dirty": "dirty", "ripped": "ripped", "full": "full", "squished": "squished", "peeled": "peeled", "broken": "broken", "mashed": "mashed", "pureed": "pureed", "dry": "dry", "chipped": "chipped", "spilled": "spilled", "coiled": "coiled", "wrinkled": "wrinkled", "narrow": "narrow", "fallen": "fallen", "muddy": "muddy", "sliced": "sliced", "sharp": "sharp", "unripe": "unripe", "thick": "thick", "open": "open", "standing": "standing", "ancient": "ancient", "toppled": "toppled", "weathered": "weathered", "murky": "murky", "damp": "damp", "tiny": "tiny", "grimy": "grimy", "viscous": "viscous", "empty": "empty", "scratched": "scratched", "painted": "painted", "pierced": "pierced", "draped": "draped", "loose": "loose", "browned": "browned", "foggy": "foggy", "brushed": "brushed", "dull": "dull", "wide": "wide", "winding": "winding", "frozen": "frozen", "straight": "straight", "smooth": "smooth", "worn": "worn", "melted": "melted", "pressed": "pressed", "cracked": "cracked", "bent": "bent", "ripe": "ripe", "mossy": "mossy", "modern": "modern", "raw": "raw", "lightweight": "lightweight", "creased": "creased", "curved": "curved", "huge": "huge", "tight": "tight", "crinkled": "crinkled", "wilted": "wilted", "dented": "dented", "crushed": "crushed", "tall": "tall", "short": "short", "shiny": "shiny", "clear": "clear", "splintered": "splintered", "cored": "cored", "cooked": "cooked", "clean": "clean", "deflated": "deflated", "barren": "barren", "fresh": "fresh", "caramelized": "caramelized"}